bridge/__init__.py
bridge/api_client.py
bridge/configuration.py
bridge/exceptions.py
bridge/rest.py
bridge/api/__init__.py
bridge/api/default_api.py
bridge/models/__init__.py
bridge/models/account.py
bridge/models/account_all_of.py
bridge/models/account_resources.py
bridge/models/authenticated_user.py
bridge/models/bank.py
bridge/models/bank_all_of.py
bridge/models/bank_country.py
bridge/models/bank_form.py
bridge/models/bank_resource.py
bridge/models/categories_list.py
bridge/models/category.py
bridge/models/category_all_of.py
bridge/models/edit_user_credentials_response.py
bridge/models/edit_user_credentials_response_all_of.py
bridge/models/inline_response200.py
bridge/models/inline_response2001.py
bridge/models/inline_response2002.py
bridge/models/inline_response2003.py
bridge/models/integer_id_resource.py
bridge/models/integer_id_resource_all_of.py
bridge/models/item.py
bridge/models/item_all_of.py
bridge/models/listof_banks.py
bridge/models/listof_banks_pagination.py
bridge/models/loan_details.py
bridge/models/mfa.py
bridge/models/pagination.py
bridge/models/parent_bank.py
bridge/models/refresh_status.py
bridge/models/resource.py
bridge/models/savings_details.py
bridge/models/transaction.py
bridge/models/transaction_all_of.py
bridge/models/transactions_list.py
bridge/models/user.py
bridge/models/user_all_of.py
test/__init__.py
test/test_account.py
test/test_account_all_of.py
test/test_account_resources.py
test/test_authenticated_user.py
test/test_bank.py
test/test_bank_all_of.py
test/test_bank_country.py
test/test_bank_form.py
test/test_bank_resource.py
test/test_categories_list.py
test/test_category.py
test/test_category_all_of.py
test/test_default_api.py
test/test_edit_user_credentials_response.py
test/test_edit_user_credentials_response_all_of.py
test/test_inline_response200.py
test/test_inline_response2001.py
test/test_inline_response2002.py
test/test_inline_response2003.py
test/test_integer_id_resource.py
test/test_integer_id_resource_all_of.py
pybridgeapi-0.8.8.dist-info/METADATA
pybridgeapi-0.8.8.dist-info/WHEEL
pybridgeapi-0.8.8.dist-info/top_level.txt
pybridgeapi-0.8.8.dist-info/RECORD
